klanil.py
klanil-0.0.1.dist-info/LICENSE
klanil-0.0.1.dist-info/METADATA
klanil-0.0.1.dist-info/WHEEL
klanil-0.0.1.dist-info/top_level.txt
klanil-0.0.1.dist-info/RECORD
